CHANGES.txt
DEPENDENCES.txt
README.txt
setup.py
src/ng/__init__.py
src/ng.fuzzytraverser.egg-info/PKG-INFO
src/ng.fuzzytraverser.egg-info/SOURCES.txt
src/ng.fuzzytraverser.egg-info/dependency_links.txt
src/ng.fuzzytraverser.egg-info/namespace_packages.txt
src/ng.fuzzytraverser.egg-info/not-zip-safe
src/ng.fuzzytraverser.egg-info/requires.txt
src/ng.fuzzytraverser.egg-info/top_level.txt
src/ng/fuzzytraverser/__init__.py
src/ng/fuzzytraverser/configure.zcml
src/ng/fuzzytraverser/fuzzytraverser.py
src/ng/fuzzytraverser/interfaces.py
src/ng/fuzzytraverser/ng.fuzzytraverser.txt
src/ng/fuzzytraverser/demo/__init__.py
src/ng/fuzzytraverser/demo/configure.zcml
src/ng/fuzzytraverser/etc/ng.fuzzytraverser-configure.zcml
src/ng/fuzzytraverser/etc/ng.fuzzytraverser.demo-configure.zcml
src/ng/fuzzytraverser/fuzzytraverserannotation/__init__.py
src/ng/fuzzytraverser/fuzzytraverserannotation/configure.zcml
src/ng/fuzzytraverser/fuzzytraverserannotation/fuzzytraverserannotableadapter.py
src/ng/fuzzytraverser/fuzzytraverserannotation/interfaces.py
src/ng/fuzzytraverser/fuzzytraverserannotation/browser/__init__.py
src/ng/fuzzytraverser/fuzzytraverserannotation/browser/configure.zcml
src/ng/fuzzytraverser/fuzzytraverserannotation/browser/fuzzytraverserannotableedit.py
src/ng/fuzzytraverser/fuzzytraverserinfo/__init__.py
src/ng/fuzzytraverser/fuzzytraverserinfo/configure.zcml
src/ng/fuzzytraverser/fuzzytraverserinfo/fuzzytraverserinfo.py
src/ng/fuzzytraverser/fuzzytraverserinfo/interfaces.py
src/ng/fuzzytraverser/fuzzytraverserproperties/__init__.py
src/ng/fuzzytraverser/fuzzytraverserproperties/configure.zcml
src/ng/fuzzytraverser/fuzzytraverserproperties/fuzzytraverserproperties.py
src/ng/fuzzytraverser/fuzzytraverserproperties/interfaces.py
src/ng/fuzzytraverser/fuzzytraverserproperties/browser/__init__.py
src/ng/fuzzytraverser/fuzzytraverserproperties/browser/configure.zcml
