Metadata-Version: 1.0
Name: ng.fuzzytraverser
Version: 1.0.1
Summary: The fuzzytraverser allow traverse via url issued with some corrupion
Home-page: http://www.dreambot.ru/product/DreamBotZope3Releases/ng.fuzzytraverser
Author: Andrey Orlov
Author-email: dbdt@dreambot.ru
License: GPL v2.1
Platform: UNKNOWN
Classifier: Environment :: Web Environment
Classifier: Intended Audience :: Developers
Classifier: License :: OSI Approved :: GNU General Public License (GPL)
Classifier: Programming Language :: Python
Classifier: Operating System :: OS Independent
Classifier: Topic :: Internet :: WWW/HTTP
Classifier: Framework :: Zope3
